LICENSE.md
MANIFEST.in
README.rst
pyproject.toml
requirements.core.txt
requirements.txt
setup.py
core_exporters_app/__init__.py
core_exporters_app/admin.py
core_exporters_app/apps.py
core_exporters_app/menus.py
core_exporters_app/settings.py
core_exporters_app/tasks.py
core_exporters_app/urls.py
core_exporters_app.egg-info/PKG-INFO
core_exporters_app.egg-info/SOURCES.txt
core_exporters_app.egg-info/dependency_links.txt
core_exporters_app.egg-info/requires.txt
core_exporters_app.egg-info/top_level.txt
core_exporters_app/access_control/__init__.py
core_exporters_app/access_control/api.py
core_exporters_app/commons/__init__.py
core_exporters_app/commons/constants.py
core_exporters_app/components/__init__.py
core_exporters_app/components/exported_compressed_file/__init__.py
core_exporters_app/components/exported_compressed_file/admin_site.py
core_exporters_app/components/exported_compressed_file/api.py
core_exporters_app/components/exported_compressed_file/models.py
core_exporters_app/components/exporter/__init__.py
core_exporters_app/components/exporter/admin_site.py
core_exporters_app/components/exporter/api.py
core_exporters_app/components/exporter/models.py
core_exporters_app/components/exporter/watch.py
core_exporters_app/exporters/__init__.py
core_exporters_app/exporters/discover.py
core_exporters_app/exporters/exporter.py
core_exporters_app/exporters/urls.py
core_exporters_app/exporters/blob/__init__.py
core_exporters_app/exporters/blob/models.py
core_exporters_app/exporters/blob/urls.py
core_exporters_app/exporters/json_exporter/__init__.py
core_exporters_app/exporters/json_exporter/models.py
core_exporters_app/exporters/json_exporter/urls.py
core_exporters_app/exporters/xml/__init__.py
core_exporters_app/exporters/xml/models.py
core_exporters_app/exporters/xml/urls.py
core_exporters_app/exporters/xsl/__init__.py
core_exporters_app/exporters/xsl/api.py
core_exporters_app/exporters/xsl/models.py
core_exporters_app/exporters/xsl/urls.py
core_exporters_app/exporters/xsl/static/xsl/admin/js/exporters/list/modals/add.js
core_exporters_app/exporters/xsl/static/xsl/admin/js/exporters/list/modals/add.raw.js
