Metadata-Version: 2.1
Name: core-exporters-app
Version: 2.19.0
Summary: Exporters for the curator core project
Home-page: https://github.com/usnistgov/core_exporters_app
Author: NIST IT Lab
Author-email: itl_inquiries@nist.gov
License-File: LICENSE.md
